cvtb/__init__.py
cvtb/lib/calculate.py
cvtb/lib/load.py
cvtb/lib/vis.py
cvtb/lib/utils/calculate_utils.py
cvtb/lib/utils/load_utils.py
cvtb/lib/utils/vis_utils.py
cvtb-0.0.4.dist-info/LICENSE
cvtb-0.0.4.dist-info/METADATA
cvtb-0.0.4.dist-info/WHEEL
cvtb-0.0.4.dist-info/top_level.txt
cvtb-0.0.4.dist-info/RECORD
