Metadata-Version: 2.1
Name: cvtb
Version: 0.0.4
Summary: Commonly used research tools
Author-email: Guangzhao He <alexhe2000@zju.edu.cn>
Project-URL: Homepage, https://github.com/AlexHe1234/cvtb
Project-URL: Issues, https://github.com/AlexHe1234/cvtb/issues
Classifier: Programming Language :: Python :: 3
Classifier: License :: OSI Approved :: MIT License
Classifier: Operating System :: OS Independent
Requires-Python: >=3.8
License-File: LICENSE
